rnaseqpipeline/Blast.py
rnaseqpipeline/Install.py
rnaseqpipeline/Run.py
rnaseqpipeline/__init__.py
rnaseqpipeline-0.1.data/scripts/fastaSplitter
rnaseqpipeline-0.1.data/scripts/rnaseqpipeline
rnaseqpipeline-0.1.dist-info/METADATA
rnaseqpipeline-0.1.dist-info/RECORD
rnaseqpipeline-0.1.dist-info/WHEEL
rnaseqpipeline-0.1.dist-info/top_level.txt
