Metadata-Version: 2.1
Name: rnaseqpipeline
Version: 0.1
Summary: WUR nematology rnaseq pipeline
Home-page: UNKNOWN
Author: Joris van Steenbrugge
Author-email: joris.vansteenbrugge@wur.nl
License: UNKNOWN
Platform: UNKNOWN
